skplumber/__init__.py
skplumber/__main__.py
skplumber/consts.py
skplumber/evaluators.py
skplumber/metrics.py
skplumber/pipeline.py
skplumber/progress.py
skplumber/skplumber.py
skplumber/utils.py
skplumber/primitives/__init__.py
skplumber/primitives/parammeta.py
skplumber/primitives/primitive.py
skplumber/primitives/custom_primitives/__init__.py
skplumber/primitives/custom_primitives/preprocessing.py
skplumber/primitives/sk_primitives/__init__.py
skplumber/primitives/sk_primitives/classifiers.py
skplumber/primitives/sk_primitives/preprocessing.py
skplumber/primitives/sk_primitives/regressors.py
skplumber/primitives/sk_primitives/transformers.py
skplumber/samplers/__init__.py
skplumber/samplers/onestack.py
skplumber/samplers/sampler.py
skplumber/samplers/straight.py
skplumber/tuners/__init__.py
skplumber/tuners/ga.py
skplumber/tuners/utils.py
skplumber-0.6.5.dev0.dist-info/METADATA
skplumber-0.6.5.dev0.dist-info/WHEEL
skplumber-0.6.5.dev0.dist-info/top_level.txt
skplumber-0.6.5.dev0.dist-info/RECORD
