Metadata-Version: 2.1
Name: skplumber
Version: 0.6.5.dev0
Summary: A scikit-learn based AutoML tool
Home-page: https://github.com/epeters3/skplumber
Author: Evan Peterson
Author-email: evanpeterson17@gmail.com
License: MIT
Platform: UNKNOWN
Requires-Dist: scikit-learn (>=0.21.3)
Requires-Dist: pandas (>=0.25.3)
Requires-Dist: pytest (>=5.2.4)
Requires-Dist: Cython (==0.29.14)
Requires-Dist: scipy (>=1.3.2)
Requires-Dist: colorlog (>=4.0.2)
Requires-Dist: flexga (>=1.1.1)
